{"BaseModel.ea71af60-bdde-4a39-bbfa-63fc905e6181": {"my_number": 89, "name": "My_First_Model", "__class__": "BaseModel", "updated_at": "2023-10-10T17:26:40.078493", "id": "ea71af60-bdde-4a39-bbfa-63fc905e6181", "created_at": "2023-10-10T17:26:40.078409"}}
{"BaseModel.ed123db4-cdc8-424f-bfd4-f44d87833a69": {"my_number": 89, "name": "My_First_Model", "__class__": "BaseModel", "updated_at": "2023-10-10T17:32:31.579013", "id": "ed123db4-cdc8-424f-bfd4-f44d87833a69", "created_at": "2023-10-10T17:32:31.578958"}}
{"BaseModel.ed123db4-cdc8-424f-bfd4-f44d87833a69": {"my_number": 89, "name": "My_First_Model", "__class__": "BaseModel", "updated_at": "2023-10-10T17:32:31.579013", "id": "ed123db4-cdc8-424f-bfd4-f44d87833a69", "created_at": "2023-10-10T17:32:31.578958"}}
{"BaseModel.0428576e-20d0-4b0d-8a14-ff30502cf9f5": {"my_number": 89, "name": "My_First_Model", "__class__": "BaseModel", "updated_at": "2023-10-10T17:32:44.478961", "id": "0428576e-20d0-4b0d-8a14-ff30502cf9f5", "created_at": "2023-10-10T17:32:44.478878"}}
{"BaseModel.0428576e-20d0-4b0d-8a14-ff30502cf9f5": {"my_number": 89, "name": "My_First_Model", "__class__": "BaseModel", "updated_at": "2023-10-10T17:32:44.478961", "id": "0428576e-20d0-4b0d-8a14-ff30502cf9f5", "created_at": "2023-10-10T17:32:44.478878"}}
{"BaseModel.759233dd-48f8-4e39-a059-0458be3bbe25": {"my_number": 89, "name": "My_First_Model", "__class__": "BaseModel", "updated_at": "2023-10-10T17:33:06.382771", "id": "759233dd-48f8-4e39-a059-0458be3bbe25", "created_at": "2023-10-10T17:33:06.382705"}}
{"BaseModel.759233dd-48f8-4e39-a059-0458be3bbe25": {"my_number": 89, "name": "My_First_Model", "__class__": "BaseModel", "updated_at": "2023-10-10T17:33:06.382771", "id": "759233dd-48f8-4e39-a059-0458be3bbe25", "created_at": "2023-10-10T17:33:06.382705"}}